memoria/__init__.py
memoria/abstractor.py
memoria/engram.py
memoria/history_manager.py
memoria/memoria.py
memoria/sparse_tensor.py
memoria/types.py
memoria/utils.py
memoria_pytorch-1.1.0.dist-info/LICENSE
memoria_pytorch-1.1.0.dist-info/METADATA
memoria_pytorch-1.1.0.dist-info/WHEEL
memoria_pytorch-1.1.0.dist-info/top_level.txt
memoria_pytorch-1.1.0.dist-info/RECORD
