Metadata-Version: 2.1
Name: memoria-pytorch
Version: 1.1.0
Summary: Memoria is a human-inspired memory architecture for neural networks.
Home-page: https://github.com/cosmoquester/memoria.git
Author: Park Sangjun
Keywords: memoria,hebbian,memory,transformer
Classifier: Programming Language :: Python :: 3
Classifier: License :: OSI Approved :: MIT License
Classifier: Topic :: Scientific/Engineering :: Artificial Intelligence
Requires-Python: >=3.10
License-File: LICENSE
Requires-Dist: torch
